netlibpp_cpy.cpython-313-darwin.so
netlibpp/__init__.pyi
netlibpp/__init__.py
netlibpp/.dylibs/libomp.dylib
netlibpp-0.0.11.dist-info/RECORD
netlibpp-0.0.11.dist-info/WHEEL
netlibpp-0.0.11.dist-info/top_level.txt
netlibpp-0.0.11.dist-info/METADATA
