Metadata-Version: 2.1
Name: netlibpp
Version: 0.0.11
Summary: A Python lib for geometric complexes construction
Author-email: Victor <vactor.pavlov.vadimovich@gmail.com>
Maintainer-email: Victor <vactor.pavlov.vadimovich@gmail.com>
Project-URL: Source, https://github.com/Kurkuzabra/NetLibpp/blob/develop/include/graph_func.cpp
Keywords: geometry,complexes,cpython
Classifier: Development Status :: 3 - Alpha
Classifier: Intended Audience :: Developers
Classifier: Programming Language :: Python :: 3
Classifier: Programming Language :: Python :: 3.12
Classifier: Programming Language :: Python :: 3.13
Classifier: Programming Language :: Python :: 3 :: Only
Requires-Python: >=3.6
Provides-Extra: dev
Requires-Dist: check-manifest ; extra == 'dev'
